README.rst
setup.py
Banzai/Banzai.py
Banzai/__init__.py
Banzai_NGS.egg-info/PKG-INFO
Banzai_NGS.egg-info/SOURCES.txt
Banzai_NGS.egg-info/dependency_links.txt
Banzai_NGS.egg-info/not-zip-safe
Banzai_NGS.egg-info/top_level.txt