Metadata-Version: 1.1
Name: Banzai-NGS
Version: 0.0.5
Summary: Banzai is a Microbial Genomics Next Generation Sequencing (NGS) Pipeline Tool
Home-page: https://github.com/mscook/Banzai-MicrobialGenomics-Pipeline
Author: Mitchell Stanton-Cook
Author-email: m.stantoncook@gmail.com
License: GPLv2
Platform: UNKNOWN
Classifier: Development Status :: 3 - Alpha
Classifier: Environment :: Console
Classifier: Intended Audience :: Science/Research
Classifier: License :: OSI Approved
Classifier: Natural Language :: English
Classifier: Operating System :: POSIX :: Linux
Classifier: Programming Language :: Python
Classifier: Programming Language :: Python :: 2.7
Classifier: Programming Language :: Python :: 2 :: Only
Classifier: Topic :: Scientific/Engineering :: Bio-Informatics
